<?xml version="1.0" encoding="UTF-8"?>
<!DOCTYPE mapper PUBLIC "-//mybatis.org//DTD Mapper 3.0//EN" "http://mybatis.org/dtd/mybatis-3-mapper.dtd">
<mapper namespace="com.scxd.dao.mapper.SysIfLogMapper">


  <insert id="insert" parameterType="com.scxd.beans.pojo.SysIfLogWithBLOBs">
    <!--
      WARNING - @mbggenerated
      This element is automatically generated by MyBatis Generator, do not modify.
    -->
    insert into SYS_IF_LOG (ID, CJSJ, JKID, 
      GLBM, WYM, INDATA, OUTDATA,ERRORMSG
      )
    values (#{id,jdbcType=VARCHAR}, #{cjsj,jdbcType=TIMESTAMP}, #{jkid,jdbcType=VARCHAR}, 
      #{glbm,jdbcType=VARCHAR}, #{wym,jdbcType=VARCHAR}, #{indata,jdbcType=CLOB}, #{outdata,jdbcType=CLOB},
    #{errormsg,jdbcType=CLOB}
      )
  </insert>
  <insert id="insertSelective" parameterType="com.scxd.beans.pojo.SysIfLogWithBLOBs">
    <!--
      WARNING - @mbggenerated
      This element is automatically generated by MyBatis Generator, do not modify.
    -->
    insert into SYS_IF_LOG
    <trim prefix="(" suffix=")" suffixOverrides=",">
      <if test="id != null">
        ID,
      </if>
      <if test="cjsj != null">
        CJSJ,
      </if>
      <if test="jkid != null">
        JKID,
      </if>
      <if test="glbm != null">
        GLBM,
      </if>
      <if test="wym != null">
        WYM,
      </if>
      <if test="indata != null">
        INDATA,
      </if>
      <if test="outdata != null">
        OUTDATA,
      </if>
    </trim>
    <trim prefix="values (" suffix=")" suffixOverrides=",">
      <if test="id != null">
        #{id,jdbcType=VARCHAR},
      </if>
      <if test="cjsj != null">
        #{cjsj,jdbcType=TIMESTAMP},
      </if>
      <if test="jkid != null">
        #{jkid,jdbcType=VARCHAR},
      </if>
      <if test="glbm != null">
        #{glbm,jdbcType=VARCHAR},
      </if>
      <if test="wym != null">
        #{wym,jdbcType=VARCHAR},
      </if>
      <if test="indata != null">
        #{indata,jdbcType=CLOB},
      </if>
      <if test="outdata != null">
        #{outdata,jdbcType=CLOB},
      </if>
    </trim>
  </insert>
  <update id="updateByPrimaryKeySelective" parameterType="com.scxd.beans.pojo.SysIfLogWithBLOBs">
    <!--
      WARNING - @mbggenerated
      This element is automatically generated by MyBatis Generator, do not modify.
    -->
    update SYS_IF_LOG
    <set>
      <if test="cjsj != null">
        CJSJ = #{cjsj,jdbcType=TIMESTAMP},
      </if>
      <if test="jkid != null">
        JKID = #{jkid,jdbcType=VARCHAR},
      </if>
      <if test="glbm != null">
        GLBM = #{glbm,jdbcType=VARCHAR},
      </if>
      <if test="wym != null">
        WYM = #{wym,jdbcType=VARCHAR},
      </if>
      <if test="indata != null">
        INDATA = #{indata,jdbcType=CLOB},
      </if>
      <if test="outdata != null">
        OUTDATA = #{outdata,jdbcType=CLOB},
      </if>
    </set>
    where ID = #{id,jdbcType=VARCHAR}
  </update>
  <update id="updateByPrimaryKeyWithBLOBs" parameterType="com.scxd.beans.pojo.SysIfLogWithBLOBs">
    <!--
      WARNING - @mbggenerated
      This element is automatically generated by MyBatis Generator, do not modify.
    -->
    update SYS_IF_LOG
    set CJSJ = #{cjsj,jdbcType=TIMESTAMP},
      JKID = #{jkid,jdbcType=VARCHAR},
      GLBM = #{glbm,jdbcType=VARCHAR},
      WYM = #{wym,jdbcType=VARCHAR},
      INDATA = #{indata,jdbcType=CLOB},
      OUTDATA = #{outdata,jdbcType=CLOB},
    ERRORMSG = #{errormsg,jdbcType=CLOB}
    where ID = #{id,jdbcType=VARCHAR}
  </update>
  <update id="updateByPrimaryKey" parameterType="com.scxd.beans.pojo.SysIfLog">
    <!--
      WARNING - @mbggenerated
      This element is automatically generated by MyBatis Generator, do not modify.
    -->
    update SYS_IF_LOG
    set CJSJ = #{cjsj,jdbcType=TIMESTAMP},
      JKID = #{jkid,jdbcType=VARCHAR},
      GLBM = #{glbm,jdbcType=VARCHAR},
      WYM = #{wym,jdbcType=VARCHAR}
    where ID = #{id,jdbcType=VARCHAR}
  </update>
</mapper>